ngr_spider/__init__.py
ngr_spider/cli.py
ngr_spider/constants.py
ngr_spider/csw_client.py
ngr_spider/decorators.py
ngr_spider/models.py
ngr_spider/ogc_api_features.py
ngr_spider/ogc_api_tiles.py
ngr_spider/util.py
ngr_services_spider-0.7.0.dist-info/LICENSE
ngr_services_spider-0.7.0.dist-info/METADATA
ngr_services_spider-0.7.0.dist-info/WHEEL
ngr_services_spider-0.7.0.dist-info/entry_points.txt
ngr_services_spider-0.7.0.dist-info/top_level.txt
ngr_services_spider-0.7.0.dist-info/RECORD
