Metadata-Version: 2.1
Name: ngr-services-spider
Version: 0.7.0
Summary: test
License: MIT
Keywords: ngr,csw,pdok,ows
Classifier: Programming Language :: Python :: 3
Classifier: Programming Language :: Python :: 3 :: Only
Classifier: Programming Language :: Python :: 3.10
Requires-Python: >=3.10.6
License-File: LICENSE
Requires-Dist: azure-storage-blob (>=12.14.1)
Requires-Dist: dataclass-wizard (>=0.22.2)
Requires-Dist: jq (>=1.3.0)
Requires-Dist: lxml (>=4.9.1)
Requires-Dist: OWSLib (>=0.28.1)
Requires-Dist: requests (>=2.25.0)
Provides-Extra: dev
Requires-Dist: black ; extra == 'dev'
Requires-Dist: mypy ; extra == 'dev'
Requires-Dist: autoflake ; extra == 'dev'
Requires-Dist: isort ; extra == 'dev'
